package_name_iurywmp/__init__.py
package_name_iurywmp/file1_name.py
package_name_iurywmp/file2_name.py
package_name_iurywmp-0.0.1.dist-info/METADATA
package_name_iurywmp-0.0.1.dist-info/WHEEL
package_name_iurywmp-0.0.1.dist-info/top_level.txt
package_name_iurywmp-0.0.1.dist-info/RECORD
