Metadata-Version: 2.1
Name: package-name-iurywmp
Version: 0.0.1
Summary: This is a test file for DIO bootcamp
Home-page: https://github.com/iurywmp/image-processing-package
Author: iurywmp
Author-email: iuryprobo@gmail.com
Requires-Python: >=3.8
Requires-Dist: matplotlib
Requires-Dist: numpy
Requires-Dist: scikit-image >=0.16.1
